{
  "bg.png": "bg-1ea496c49d.png",
  "bj.jpg": "bj-84419b902a.jpg",
  "download-cn.png": "download-cn-29b1131ca2.png",
  "download-en.png": "download-en-a06f6f5523.png",
  "download-tw.png": "download-tw-7996d2ac46.png",
  "guide-cn.png": "guide-cn-5c2c79bfc5.png",
  "guide-en.png": "guide-en-0f09d0d64a.png",
  "guide-tw.png": "guide-tw-dcdce167ba.png",
  "ios-arrow.png": "ios-arrow-4d81c9ee43.png",
  "ios-cn-01.jpg": "ios-cn-01-aeaa2170b4.jpg",
  "ios-cn-02.jpg": "ios-cn-02-1a07126ea1.jpg",
  "ios-cn-03.jpg": "ios-cn-03-fb6b3bb636.jpg",
  "ios-en-01.jpg": "ios-en-01-5d4c0baefb.jpg",
  "ios-en-02.jpg": "ios-en-02-c9122825ca.jpg",
  "ios-en-03.jpg": "ios-en-03-5ee823b7ee.jpg",
  "ios-new-phone-cn.png": "ios-new-phone-cn-4dd8e0e537.png",
  "ios-new-phone-en.png": "ios-new-phone-en-e4b973ca56.png",
  "ios-new-phone-tw.png": "ios-new-phone-tw-b8f405860a.png",
  "ios-tw-01.jpg": "ios-tw-01-495df2d8c0.jpg",
  "ios-tw-02.jpg": "ios-tw-02-9ea58d3c98.jpg",
  "ios-tw-03.jpg": "ios-tw-03-5ce0c3077c.jpg",
  "logo.png": "logo-bc90b4caf8.png",
  "new-phone-cn.png": "new-phone-cn-26643fb9cb.png",
  "new-phone-en.png": "new-phone-en-5976efaf2e.png",
  "new-phone-tw.png": "new-phone-tw-f5edcbab8a.png"
}